solceasy/__init__.py
solceasy/__main__.py
solceasy/solceasy.py
solceasy/templates/template.js
solceasy-0.2.data/scripts/solceasy
solceasy-0.2.dist-info/LICENSE
solceasy-0.2.dist-info/METADATA
solceasy-0.2.dist-info/WHEEL
solceasy-0.2.dist-info/top_level.txt
solceasy-0.2.dist-info/RECORD
