Metadata-Version: 2.1
Name: solceasy
Version: 0.2
Summary: Um utilitário para compilação e deploy de contratos ethereum
Home-page: https://github.com/diego-lima/solceasy
Author: Diego Lima
Author-email: ddddiegolima@gmail.com
License: UNKNOWN
Platform: UNKNOWN
Classifier: Programming Language :: Python :: 3
Classifier: License :: OSI Approved :: MIT License
Classifier: Operating System :: OS Independent
License-File: LICENSE
